setup.py
Arko/__init__.py
Arko.egg-info/PKG-INFO
Arko.egg-info/SOURCES.txt
Arko.egg-info/dependency_links.txt
Arko.egg-info/top_level.txt