Metadata-Version: 2.1
Name: Arko
Version: 0.0.1
Summary: Arko
Home-page: UNKNOWN
Author: Anish Agrawal
Author-email: your.email@example.com
License: UNKNOWN
Platform: UNKNOWN
